tcubed-1.0.0.dist-info/licenses/LICENSE
ttt/__init__.py
ttt/cli.py
ttt/slides.py
ttt/tut.py
ttt/utils.py
tcubed-1.0.0.dist-info/METADATA
tcubed-1.0.0.dist-info/WHEEL
tcubed-1.0.0.dist-info/entry_points.txt
tcubed-1.0.0.dist-info/top_level.txt
tcubed-1.0.0.dist-info/RECORD
