Metadata-Version: 2.4
Name: tcubed
Version: 1.0.0
Summary: This is TicTacToe in the terminal! But different...
Author-email: thesignumt <tcrrxzz@gmail.com>
License-Expression: MIT
Project-URL: Repository, https://github.com/thesignumt/tcubed
Requires-Python: >=3.10
License-File: LICENSE
Requires-Dist: pyfiglet
Dynamic: license-file
